src/__init__.py
src/conf_log.py
src/config.py
src/driver_setup.py
src/email_content.py
src/email_extractor.py
src/email_sender.py
src/fetcher.py
src/link_extractor.py
src/main.py
src/run_getemail.py
src/run_getlink.py
src/run_sendmail.py
src/test.py
src/utils.py
ResumeRover-0.0.2.dist-info/LICENSE
ResumeRover-0.0.2.dist-info/METADATA
ResumeRover-0.0.2.dist-info/WHEEL
ResumeRover-0.0.2.dist-info/top_level.txt
ResumeRover-0.0.2.dist-info/RECORD
