Metadata-Version: 2.1
Name: ResumeRover
Version: 0.0.2
Summary: Email Handler is a simple and efficient tool for managing and sending emails using Python. This project allows you to automate the sending of emails and easily work with a list of email addresses.
Home-page: https://github.com/pydevcasts/ResumeRover
Author: Siyamak Abasnezhad
Author-email: Siyamak <pydevcasts@gmail.com>
Project-URL: Homepage, https://github.com/pydevcasts/ResumeRover
Project-URL: Issues, https://github.com/pydevcasts/ResumeRover/issues
Classifier: Programming Language :: Python :: 3
Classifier: License :: OSI Approved :: MIT License
Classifier: Operating System :: OS Independent
Requires-Python: >=3.8
License-File: LICENSE
